openapi_server/__init__.py
openapi_server/__main__.py
openapi_server/typing_utils.py
openapi_server/util.py
openapi_server/controllers/__init__.py
openapi_server/controllers/activities_controller.py
openapi_server/controllers/activity_descriptions_controller.py
openapi_server/controllers/activity_rates_controller.py
openapi_server/controllers/allocations_controller.py
openapi_server/controllers/bank_accounts_controller.py
openapi_server/controllers/bank_transactions_controller.py
openapi_server/controllers/bank_transfers_controller.py
openapi_server/controllers/bill_themes_controller.py
openapi_server/controllers/billable_clients_controller.py
openapi_server/controllers/billable_matters_controller.py
openapi_server/controllers/billing_settings_controller.py
openapi_server/controllers/bills_controller.py
openapi_server/controllers/calendar_entries_controller.py
openapi_server/controllers/calendar_entry_event_types_controller.py
openapi_server/controllers/calendar_visibilities_controller.py
openapi_server/controllers/calendars_controller.py
openapi_server/controllers/civil_certificated_rates_controller.py
openapi_server/controllers/civil_controlled_rates_controller.py
openapi_server/controllers/clients_controller.py
openapi_server/controllers/clio_payments_links_controller.py
openapi_server/controllers/clio_payments_payments_controller.py
openapi_server/controllers/comments_controller.py
openapi_server/controllers/communications_controller.py
openapi_server/controllers/contacts_controller.py
openapi_server/controllers/conversation_messages_controller.py
openapi_server/controllers/conversations_controller.py
openapi_server/controllers/credit_memos_controller.py
openapi_server/controllers/criminal_controlled_rates_controller.py
openapi_server/controllers/currencies_controller.py
openapi_server/controllers/custom_actions_controller.py
openapi_server/controllers/custom_field_sets_controller.py
openapi_server/controllers/custom_fields_controller.py
clio_cli-1.0.5.dist-info/METADATA
clio_cli-1.0.5.dist-info/WHEEL
clio_cli-1.0.5.dist-info/entry_points.txt
clio_cli-1.0.5.dist-info/top_level.txt
clio_cli-1.0.5.dist-info/RECORD
