Metadata-Version: 2.1
Name: clio-cli
Version: 1.0.5
Summary: Clio API Documentation
Home-page: 
Author-email: api@clio.com
Keywords: OpenAPI,Clio API Documentation
Requires-Dist: connexion ==2.14.1
Requires-Dist: swagger-ui-bundle ==0.0.9
Requires-Dist: aiohttp-jinja2 ==1.5.0
